unified_gui_layout.py
amp_benchkit/__init__.py
amp_benchkit/automation.py
amp_benchkit/calibration.py
amp_benchkit/cli.py
amp_benchkit/config.py
amp_benchkit/deps.py
amp_benchkit/diagnostics.py
amp_benchkit/dsp.py
amp_benchkit/fy.py
amp_benchkit/logging.py
amp_benchkit/sweeps.py
amp_benchkit/tek.py
amp_benchkit/u3config.py
amp_benchkit/u3util.py
amp_benchkit-0.3.9.dist-info/licenses/LICENSE
amp_benchkit-0.3.9.dist-info/METADATA
amp_benchkit-0.3.9.dist-info/WHEEL
amp_benchkit-0.3.9.dist-info/entry_points.txt
amp_benchkit-0.3.9.dist-info/top_level.txt
amp_benchkit-0.3.9.dist-info/RECORD
