Metadata-Version: 2.4
Name: amp-benchkit
Version: 0.3.9
Summary: Unified GUI + LabJack tooling and installer helpers
Author: Brian Wedderburn
License-Expression: MIT
Project-URL: Homepage, https://github.com/bwedderburn/amp-benchkit
Project-URL: Documentation, https://bwedderburn.github.io/amp-benchkit/
Project-URL: Repository, https://github.com/bwedderburn/amp-benchkit
Project-URL: Issues, https://github.com/bwedderburn/amp-benchkit/issues
Project-URL: Changelog, https://github.com/bwedderburn/amp-benchkit/blob/main/CHANGELOG.md
Keywords: labjack,instrumentation,gui,automation
Classifier: Development Status :: 4 - Beta
Classifier: Intended Audience :: Developers
Classifier: Intended Audience :: Science/Research
Classifier: Programming Language :: Python :: 3
Classifier: Programming Language :: Python :: 3 :: Only
Classifier: Programming Language :: Python :: 3.10
Classifier: Programming Language :: Python :: 3.11
Classifier: Programming Language :: Python :: 3.12
Classifier: Operating System :: POSIX :: Linux
Classifier: Environment :: Console
Classifier: Environment :: X11 Applications :: Qt
Classifier: Topic :: Scientific/Engineering
Classifier: Topic :: Scientific/Engineering :: Information Analysis
Classifier: Topic :: Scientific/Engineering :: Interface Engine/Protocol Translator
Classifier: Topic :: Scientific/Engineering :: Visualization
Classifier: Topic :: System :: Hardware :: Universal Serial Bus (USB)
Classifier: Topic :: Utilities
Classifier: Framework :: Pytest
Requires-Python: >=3.10
License-File: LICENSE
Requires-Dist: numpy==2.3.3
Requires-Dist: matplotlib==3.10.7
Requires-Dist: pyvisa==1.15.0
Requires-Dist: pyserial==3.5
Requires-Dist: LabJackPython==2.1.0
Provides-Extra: gui
Requires-Dist: PySide6==6.10.0; extra == "gui"
Requires-Dist: PyQt5==5.15.11; extra == "gui"
Provides-Extra: dev
Requires-Dist: black; extra == "dev"
Requires-Dist: ruff; extra == "dev"
Requires-Dist: mypy; extra == "dev"
Requires-Dist: pre-commit; extra == "dev"
Provides-Extra: test
Requires-Dist: pytest; extra == "test"
Requires-Dist: pytest-cov; extra == "test"
Provides-Extra: publish
Requires-Dist: build; extra == "publish"
Requires-Dist: twine; extra == "publish"
Requires-Dist: wheel; extra == "publish"
Requires-Dist: setuptools; extra == "publish"
Provides-Extra: docs
Requires-Dist: mkdocs>=1.6; extra == "docs"
Requires-Dist: mkdocs-material>=9.5; extra == "docs"
Dynamic: license-file
